Workbook

Sheet Test Cases
A1: Test Case ID | B1: Requirement ID | C1: Scenario ID | D1: Module | E1: Title | F1: Preconditions | G1: Test Data | H1: Steps | I1: Expected Result | J1: Priority | K1: Test Type | L1: Execution Status | M1: Actual Result | N1: Defect ID | O1: Evidence / Screenshot
A2: TC_FS_001 | B2: REQ-FS-001 | C2: TS_FS_001 | D2: Flight Search | E2: Verify successful flight search using valid mandatory search criteria | F2: User has access to the flight search page. | G2: Valid origin; valid destination; supported future date; 1 Adult | H2: 1. Open flight search page 2. Enter valid origin 3. Enter valid destination 4. Select a supported future date 5. Select 1 Adult 6. Click Search | I2: Available flights matching the selected search criteria should be displayed. | J2: High | K2: Positive | L2: Passed | M2: The system successfully displayed available flight results for DEL to DXB using valid future travel dates, 1 passenger, and Economy class. The returned results matched the selected route and search criteria. | O2: TC_FS_001_valid_search_results.jpg
A3: TC_FS_002 | B3: REQ-FS-002 | C3: TS_FS_002 | D3: Flight Search | E3: Verify flight search is prevented when origin and destination are the same | F3: User is on the flight search page. | G3: Origin = same as Destination | H3: 1. Select an origin 2. Select the same location as destination 3. Attempt to search | I3: The system should prevent the search and show appropriate validation or block the invalid combination. | J3: High | K3: Negative | L3: Failed | M3: The system allowed the user to search with the same origin and destination (DEL → DEL) and navigated to the results page showing 0 flights instead of preventing the invalid search combination. | N3: DEF-FS-001 | O3: evidence/screenshots/DEF_FS_001_same_origin_destination_allowed.jpg
A4: TC_FS_003 | B4: REQ-FS-003 | C4: TS_FS_003 | D4: Flight Search | E4: Verify past departure date is prevented or appropriately handled | F4: User is on the flight search page. | G4: Departure date = past date | H4: 1. Enter valid origin and destination 2. Attempt to select/enter a past departure date 3. Attempt to search | I4: Past travel date should not be accepted; the system should prevent submission or show appropriate validation. | J4: High | K4: Negative | L4: Passed | M4: Past departure dates are disabled in the date picker and cannot be selected. The system allows only the current/supported future travel dates. | O4: TC_FS_003_past_date_disabled.jpg
A5: TC_FS_004 | B5: REQ-FS-004 | C5: TS_FS_004 | D5: Flight Search | E5: Verify infant cannot be selected without an accompanying adult | F5: Passenger selector is available. | G5: Adult = 0; Infant = 1 | H5: 1. Open passenger selector 2. Set adult count to 0 if permitted 3. Attempt to select 1 infant 4. Continue/search | I5: The system should prevent an infant-only passenger combination or display appropriate validation. | J5: High | K5: Business Rule | L5: Passed
A6: TC_FS_005 | B6: REQ-FS-002 | C6: TS_FS_005 | D6: Flight Search | E6: Verify search is prevented when destination is blank | F6: User is on the flight search page. | G6: Valid origin; destination blank; supported future date | H6: 1. Enter a valid origin 2. Leave destination blank 3. Complete remaining mandatory fields 4. Click Search | I6: The system should prevent search and indicate that destination is required. | J6: High | K6: Negative | L6: Passed
A7: TC_FS_006 | B7: REQ-FS-005 | C7: TS_FS_006 | D7: Flight Search | E7: Verify search results match the selected origin and destination | F7: A valid flight search can be submitted. | G7: Valid route supported by SUT | H7: 1. Search using valid origin and destination 2. Review returned flight cards/results | I7: Every displayed result should correspond to the selected route or clearly documented connecting itinerary. | J7: High | K7: Functional | L7: Passed
A8: TC_FS_007 | B8: REQ-FS-005 | C8: TS_FS_007 | D8: Flight Search | E8: Verify search results correspond to the selected travel date | F8: A valid flight search can be submitted. | G8: Supported future date | H8: 1. Search for a supported route on a future date 2. Review returned results | I8: Displayed results should correspond to the selected travel date, subject to itinerary rules shown by the system. | J8: High | K8: Functional | L8: Passed
A9: TC_FS_008 | B9: REQ-FS-005 | C9: TS_FS_008 | D9: Flight Search | E9: Verify system behavior when no flights are available | F9: User can submit a valid search. | G9: Route/date combination with no inventory, where reproducible | H9: 1. Enter valid search criteria that return no inventory 2. Click Search | I9: The system should show a clear no-results state and should not display unrelated flight inventory. | J9: Medium | K9: Negative | L9: Passed
A10: TC_FARE_001 | B10: REQ-FARE-001 | C10: TS_FARE_001 | D10: Fare | E10: Verify fare is displayed for a selected flight | F10: Flight search returns at least one result. | G10: Any available result | H10: 1. Perform a valid flight search 2. Review fare shown for an available flight | I10: A fare should be visible for the selectable flight/fare option. | J10: High | K10: Functional | L10: Passed
A11: TC_FARE_002 | B11: REQ-FARE-002 | C11: TS_FARE_002 | D11: Fare | E11: Verify total fare calculation includes applicable components correctly | F11: Fare breakdown is available. | G11: Base fare, taxes/fees, optional ancillaries where supported | H11: 1. Select a flight 2. Review fare breakdown 3. Calculate displayed components 4. Compare with total payable amount | I11: Total payable amount should equal the sum of applicable fare components minus valid discounts. | J11: High | K11: Functional | L11: Passed
A12: TC_FARE_003 | B12: REQ-FARE-003 | C12: TS_FARE_003 | D12: Fare | E12: Verify total fare recalculates when passenger count changes | F12: Passenger count can be modified before payment. | G12: 1 Adult then 2 Adults, where supported | H12: 1. Search/select a flight for 1 adult 2. Note total fare 3. Change passenger count to 2 adults 4. Recheck total fare | I12: Fare should be recalculated according to the updated passenger count and applicable pricing rules. | J12: High | K12: Functional | L12: Passed
A13: TC_FARE_004 | B13: REQ-FARE-004 | C13: TS_FARE_005 | D13: Fare | E13: Verify fare remains consistent from selection to booking review | F13: User can continue from flight selection to review. | G13: Selected flight/fare | H13: 1. Note fare at flight selection 2. Continue to review page 3. Compare fare values | I13: Fare should remain consistent unless a change is explicitly communicated before continuation/payment. | J13: High | K13: Regression | L13: Passed
A14: TC_FARE_005 | B14: REQ-FARE-004 | C14: TS_FARE_007 | D14: Fare | E14: Verify final payable amount displayed before payment is correct | F14: User has reached payment review. | G14: Booking with fare components displayed | H14: 1. Review final payable amount 2. Compare with previously displayed fare breakdown | I14: The final amount should match the correctly calculated booking total. | J14: High | K14: Functional | L14: Passed
A15: TC_PAX_001 | B15: REQ-PAX-001 | C15: TS_PAX_001 | D15: Passenger | E15: Verify valid passenger details are accepted | F15: A flight/fare has been selected. | G15: Valid passenger details supported by SUT | H15: 1. Enter valid passenger details 2. Continue to next step | I15: Valid passenger details should be accepted and user should be able to continue. | J15: High | K15: Positive | L15: Passed
A16: TC_PAX_002 | B16: REQ-PAX-001 | C16: TS_PAX_002 | D16: Passenger | E16: Verify mandatory passenger fields cannot be left blank | F16: Passenger details page is displayed. | G16: Leave one mandatory field blank | H16: 1. Leave a mandatory passenger field blank 2. Complete other required fields 3. Attempt to continue | I16: The system should prevent continuation and identify the missing mandatory information. | J16: High | K16: Negative | L16: Passed | M16: The Book/Continue option remained disabled when a mandatory passenger field was left blank, preventing the user from proceeding with incomplete passenger details
A17: TC_PAX_003 | B17: REQ-PAX-002 | C17: TS_PAX_003 | D17: Passenger | E17: Verify passenger name length boundary handling | F17: Passenger details page is displayed. | G17: Name at supported maximum length and one character beyond, where limit is known | H17: 1. Enter a name at the documented/observed maximum 2. Attempt to continue 3. Repeat with value exceeding the limit | I17: Boundary value should be handled according to the field rules; unsupported excessive input should not silently corrupt data. | J17: Medium | K17: Boundary | L17: Failed | M17: The passenger name field accepted an excessively long value without validation or character-limit indication. After booking, the passenger name was silently truncated on the invoice. | N17: DEF-PAX-001
A18: TC_PAX_004 | B18: REQ-PAX-004 | C18: TS_PAX_004 | D18: Passenger | E18: Verify duplicate passenger details are appropriately handled | F18: Booking supports more than one passenger. | G18: Two passenger entries with identical details | H18: 1. Add multiple passengers 2. Enter identical details for two passengers 3. Attempt to continue | I18: The system should handle duplicate passenger details according to the defined business rule and should not create ambiguous traveler records. | J18: Medium | K18: Business Rule | L18: Passed
A19: TC_PAX_005 | B19: REQ-PAX-003 | C19: TS_PAX_005 | D19: Passenger | E19: Verify supported passenger categories are handled correctly | F19: Passenger selector/details supports passenger types. | G19: Adult/Child/Infant where supported | H19: 1. Select each supported passenger type in valid combinations 2. Continue through passenger entry | I19: The system should apply the appropriate validation and pricing rules for each supported passenger type. | J19: High | K19: Functional | L19: Failed | N19: DEF-PAX-002
A20: TC_PAY_001 | B20: REQ-PAY-001 | C20: TS_PAY_001 | D20: Payment | E20: Verify successful payment using a supported test payment method | F20: Booking is ready for payment; sandbox/test payment method is available. | G20: Supported sandbox/test payment data | H20: 1. Proceed to payment 2. Select a supported test payment method 3. Enter valid test details 4. Submit payment | I20: Payment should complete successfully and transaction/booking status should update appropriately. | J20: Critical | K20: Positive | L20: Blocked | N20: DEF-PAY-001
A21: TC_PAY_002 | B21: REQ-PAY-002 | C21: TS_PAY_002 | D21: Payment | E21: Verify failed payment does not create a successfully paid booking | F21: Booking is ready for payment. | G21: Sandbox/test data that produces failure, if supported | H21: 1. Submit a payment designed to fail 2. Review payment and booking status | I21: Payment should be marked failed/unsuccessful and booking should not be incorrectly marked as successfully paid. | J21: Critical | K21: Negative | L21: Passed | M21: Payment was cancelled successfully. The system displayed that no charges were made, the Booking Status remained Pending, and the Payment Status remained Unpaid.
A22: TC_PAY_003 | B22: REQ-PAY-003 | C22: TS_PAY_003 | D22: Payment | E22: Verify repeated payment submission does not create duplicate charges | F22: Booking is ready for payment. | G22: Same payment attempt submitted repeatedly where safe/test-mode | H22: 1. Submit payment 2. Repeat/click submit again during processing where reproducible 3. Review transaction outcome | I22: Only one charge/transaction side effect should be created for the booking. | J22: Critical | K22: Risk-Based | L22: Passed | M22: After successful payment, the booking status changed to Confirmed and payment status changed to Paid. The Make Payment option was no longer displayed, preventing another payment attempt from being initiated through the invoice UI.
A23: TC_PAY_004 | B23: REQ-PAY-003 | C23: TS_PAY_004 | D23: Payment | E23: Verify repeated payment submission does not create duplicate bookings | F23: Booking is ready for payment. | G23: Same booking/payment request | H23: 1. Submit payment repeatedly where safe/test-mode 2. Review resulting booking records | I23: Only one logical booking should be created for the same successful transaction/request. | J23: Critical | K23: Risk-Based | L23: Passed | M23: After successful payment and page refresh, a single confirmed booking remained associated with booking reference 64978746. No additional booking reference was generated through the observed payment flow.
A24: TC_PAY_005 | B24: REQ-PAY-004 | C24: TS_PAY_005 | D24: Payment | E24: Verify payment timeout is handled safely | F24: Timeout can be simulated or tested at design level if not supported by SUT. | G24: Payment request timeout scenario | H24: 1. Initiate payment 2. Simulate/observe timeout where supported 3. Check UI status and retry behavior | I24: The user should not receive a misleading success/failure state and retry should not cause duplicate payment/booking side effects. | J24: Critical | K24: Negative | L24: Blocked | M24: Payment timeout could not be safely and deterministically simulated using the available demo UI and Stripe Sandbox flow. Test retained as a design-level scenario.
A25: TC_PAY_006 | B25: REQ-PAY-005 | C25: TS_PAY_006 | D25: Payment | E25: Verify charged amount matches final payable booking amount | F25: Booking has a known final payable amount. | G25: Final amount from review page | H25: 1. Note final payable amount 2. Complete test payment 3. Compare transaction amount with booking amount | I25: Transaction amount should match the final payable booking amount. | J25: Critical | K25: Functional | L25: Passed | M25: The final payable amount displayed on the booking invoice was USD 104,410.75. Stripe Sandbox displayed the same transaction amount of USD 104,410.75, and the confirmed paid invoice retained the same total amount. No discrepancy was observed.
A26: TC_PAY_007 | B26: REQ-PAY-005 | C26: TS_PAY_009 | D26: Payment | E26: Verify handling when payment succeeds but booking/PNR generation fails | F26: Scenario can be simulated at design level if not reproducible in demo. | G26: Successful payment + downstream booking/PNR failure | H26: 1. Record payment transaction reference 2. Observe/simulate downstream booking failure 3. Check booking/PNR status 4. Check retry/reversal/recovery behavior | I26: System should prevent duplicate transactions and provide safe reconciliation, retry, reversal, or recovery behavior. | J26: Critical | K26: Integration | L26: Not Executed
A27: TC_PNR_001 | B27: REQ-PNR-001 | C27: TS_PNR_001 | D27: Booking / PNR | E27: Verify successful booking creates a booking record | F27: Payment/booking prerequisites are satisfied. | G27: Valid completed booking flow | H27: 1. Complete valid booking flow 2. Review confirmation | I27: A booking record/reference should be created after successful booking completion. | J27: Critical | K27: Positive | L27: Not Executed
A28: TC_PNR_002 | B28: REQ-PNR-002 | C28: TS_PNR_002 | D28: Booking / PNR | E28: Verify successful booking generates a non-null non-empty PNR | F28: A booking completes successfully. | G28: Successful booking | H28: 1. Complete booking 2. Inspect confirmation/reference details | I28: A valid PNR/booking reference should be present and should not be null or empty. | J28: Critical | K28: Functional | L28: Not Executed
A29: TC_PNR_003 | B29: REQ-PNR-003 | C29: TS_PNR_003 | D29: Booking / PNR | E29: Verify passenger details stored in booking are correct | F29: A booking has been created. | G29: Known passenger test data | H29: 1. Complete booking using known passenger data 2. Retrieve/review booking 3. Compare passenger details | I29: Stored/displayed passenger details should match the data entered during booking. | J29: High | K29: Functional | L29: Not Executed
A30: TC_PNR_004 | B30: REQ-PNR-003 | C30: TS_PNR_004 | D30: Booking / PNR | E30: Verify itinerary details stored in booking are correct | F30: A booking has been created. | G30: Known origin/destination/date/flight | H30: 1. Complete booking 2. Retrieve/review booking 3. Compare itinerary with selected flight | I30: Booking itinerary should match the selected route, date, and flight/segment information. | J30: High | K30: Functional | L30: Not Executed
A31: TC_PNR_005 | B31: REQ-PNR-003 | C31: TS_PNR_005 | D31: Booking / PNR | E31: Verify fare stored in booking matches final payable amount | F31: A booking has been created. | G31: Known final payable amount | H31: 1. Note final payable amount 2. Complete booking 3. Retrieve/review booking fare | I31: Stored booking fare should match the final payable amount, subject to any clearly disclosed post-booking charges. | J31: High | K31: Functional | L31: Not Executed
A32: TC_PNR_006 | B32: REQ-PNR-004 | C32: TS_PNR_007 | D32: Booking / PNR | E32: Verify booking can be retrieved using supported booking reference/PNR | F32: A valid booking/reference exists. | G32: Valid PNR/booking reference | H32: 1. Open manage/retrieve booking function 2. Enter valid reference and any required verification data 3. Submit | I32: The correct booking should be retrieved. | J32: High | K32: Positive | L32: Passed | M32: Booking reference 80882104 was successfully retrieved through the Admin booking interface. The retrieved booking displayed the expected DEL → DXB itinerary, passenger/customer information, Booking Status as Confirmed, and Payment Status as Paid. | N32: DEF-CAN-001
A33: TC_CAN_001 | B33: REQ-CAN-001 | C33: TS_CAN_001 | D33: Cancellation | E33: Verify eligible confirmed booking can be cancelled | F33: A cancellable confirmed booking exists. | G33: Eligible booking | H33: 1. Retrieve eligible booking 2. Start cancellation 3. Confirm cancellation | I33: Cancellation should complete according to booking rules and confirmation should be shown. | J33: High | K33: Positive | L33: Failed | M33: A cancellation request was successfully submitted for confirmed booking 80882104. However, the cancellation could not be completed in the Admin portal because the booking had no issued PNR. The system displayed Booking Issue Error: Invalid JSON response from Sabre API, and the booking remained Confirmed/Paid with the cancellation request pending. | N33: DEF-CAN-001
A34: TC_CAN_002 | B34: REQ-CAN-002 | C34: TS_CAN_002 | D34: Cancellation | E34: Verify booking status updates after successful cancellation | F34: A booking has just been cancelled. | G34: Cancelled booking reference | H34: 1. Retrieve the cancelled booking 2. Review booking status | I34: Booking status should reflect cancellation consistently across relevant views. | J34: High | K34: Functional | L34: Blocked | M34: Cancellation processing is blocked because supplier booking issuance/PNR generation is incomplete.
A35: TC_CAN_003 | B35: REQ-CAN-001 | C35: TS_CAN_003 | D35: Cancellation | E35: Verify ineligible booking cannot be cancelled | F35: An ineligible/non-cancellable booking exists or scenario is simulated. | G35: Ineligible booking | H35: 1. Retrieve ineligible booking 2. Attempt cancellation | I35: The system should block cancellation and clearly communicate the applicable restriction. | J35: Medium | K35: Negative | L35: Passed | M35: Booking 81255961 was already in Cancelled status with Payment Status Refunded. The booking page did not display a Request Cancellation option, preventing another cancellation attempt.
A36: TC_REF_001 | B36: REQ-REF-001 | C36: TS_REF_001 | D36: Refund | E36: Verify eligible cancelled booking initiates refund correctly | F36: A refundable cancelled booking exists. | G36: Refund-eligible booking | H36: 1. Cancel/retrieve eligible booking 2. Initiate or observe refund process | I36: Refund should be initiated according to the applicable cancellation/fare rules. | J36: High | K36: Positive | L36: Blocked | M36: No booking with Booking Status = Cancelled and Payment Status = Paid was available in the current demo data. Available cancelled bookings were already in Refunded status, so refund initiation could not be executed or observed.
A37: TC_REF_002 | B37: REQ-REF-001 | C37: TS_REF_002 | D37: Refund | E37: Verify refundable amount is calculated correctly | F37: Refund calculation is displayed or available. | G37: Known paid amount and applicable fees/rules | H37: 1. Determine amount paid 2. Apply displayed/documented cancellation deductions 3. Compare expected and displayed refund | I37: Refundable amount should match the applicable fare/cancellation rules. | J37: High | K37: Functional | L37: Passed | M37: The refund amount displayed by the system matched the expected refundable amount based on the booking amount and applicable cancellation/refund rules.
A38: TC_E2E_001 | B38: REQ-PNR-002 | C38: TS_E2E_001 | D38: End-to-End | E38: Verify successful end-to-end booking from search to PNR generation | F38: Test-mode booking flow is available. | G38: Valid search, passenger and test payment data | H38: 1. Search flight 2. Select fare 3. Enter passenger details 4. Complete test payment 5. Review confirmation/PNR | I38: The entire flow should complete with consistent itinerary, passenger, fare, payment and booking information. | J38: Critical | K38: End-to-End | L38: Passed | M38: The end-to-end booking flow was completed successfully from flight search through fare selection, passenger entry, payment, and booking confirmation. The resulting booking information was consistent with the selected itinerary and payment details.
A39: TC_E2E_002 | B39: REQ-PAY-004 | C39: TS_E2E_003 | D39: End-to-End | E39: Verify payment retry after timeout does not create duplicate charge or booking | F39: Scenario can be simulated safely or maintained as a design-level case. | G39: Payment timeout followed by retry | H39: 1. Initiate payment 2. Simulate/observe timeout 3. Retry same transaction 4. Inspect payment and booking outcomes | I39: Retry should be idempotent or otherwise safely handled so that duplicate charges/bookings are not created. | J39: Critical | K39: Risk-Based | L39: Blocked | M39: A deterministic payment-timeout condition could not be safely reproduced in the current demo environment, so retry behavior after timeout and duplicate charge/booking protection could not be validated end to end.
A40: TC_E2E_003 | B40: REQ-FARE-004 | C40: TS_E2E_004 | D40: End-to-End | E40: Verify fare consistency across search, review and payment | F40: Valid booking flow is available. | G40: Known selected fare | H40: 1. Note fare at selection 2. Continue to review 3. Note final payable amount 4. Compare before payment | I40: Fare should remain consistent unless a change is explicitly disclosed and accepted by the user. | J40: High | K40: Regression | L40: Not Executed

Sheet Coverage Summary
A1: Airline Manual QA - Test Case Coverage Summary
A3: Metric | B3: Value | D3: Module | E3: Count | F3: % of Total
A4: Total Test Cases | B4: =COUNTA('Test Cases'!A2:A40) -> 39 | D4: Flight Search | E4: =COUNTIF('Test Cases'!D2:D40,D4) -> 8 | F4: =E4/$B$4 -> 0.20512821
A5: Critical Priority | B5: =COUNTIF('Test Cases'!J2:J40,"Critical") -> 11 | D5: Fare | E5: =COUNTIF('Test Cases'!D2:D40,D5) -> 5 | F5: =E5/$B$4 -> 0.12820513
A6: High Priority | B6: =COUNTIF('Test Cases'!J2:J40,"High") -> 24 | D6: Passenger | E6: =COUNTIF('Test Cases'!D2:D40,D6) -> 5 | F6: =E6/$B$4 -> 0.12820513
A7: Passed | B7: =COUNTIF('Test Cases'!L2:L40,"Passed") -> 23 | D7: Payment | E7: =COUNTIF('Test Cases'!D2:D40,D7) -> 7 | F7: =E7/$B$4 -> 0.17948718
A8: Failed | B8: =COUNTIF('Test Cases'!L2:L40,"Failed") -> 4 | D8: Booking / PNR | E8: =COUNTIF('Test Cases'!D2:D40,D8) -> 6 | F8: =E8/$B$4 -> 0.15384615
D9: Cancellation | E9: =COUNTIF('Test Cases'!D2:D40,D9) -> 3 | F9: =E9/$B$4 -> 0.076923077
D10: Refund | E10: =COUNTIF('Test Cases'!D2:D40,D10) -> 2 | F10: =E10/$B$4 -> 0.051282051
D11: End-to-End | E11: =COUNTIF('Test Cases'!D2:D40,D11) -> 3 | F11: =E11/$B$4 -> 0.076923077

Sheet Lists
A1: Field | B1: Allowed Values / Notes
A2: Priority | B2: Critical, High, Medium, Low
A3: Execution Status | B3: Not Executed, Passed, Failed, Blocked, Not Applicable
A4: Test Type | B4: Positive, Negative, Boundary, Functional, Business Rule, Regression, Risk-Based, Integration, End-to-End
A5: Execution Note | B5: All rows start as Not Executed. Update only after real execution.
A6: Evidence | B6: Add screenshot filename/path only when evidence exists.
A7: Project Basis | B7: Design is based on the portfolio requirements. Update test data/results based on actual SUT behavior.
